openasi/__init__.py
openasi-0.0.1.dist-info/METADATA
openasi-0.0.1.dist-info/WHEEL
openasi-0.0.1.dist-info/licenses/LICENSE
openasi-0.0.1.dist-info/RECORD
