Metadata-Version: 2.4
Name: openasi
Version: 0.0.1
Summary: OpenASI - coming soon
Project-URL: Homepage, https://github.com/alexngai/meta-learning-engine
Project-URL: Repository, https://github.com/alexngai/meta-learning-engine
License-Expression: MIT
License-File: LICENSE
Keywords: ai,asi,openasi
Classifier: Development Status :: 1 - Planning
Classifier: Intended Audience :: Developers
Classifier: License :: OSI Approved :: MIT License
Classifier: Programming Language :: Python :: 3
Classifier: Programming Language :: Python :: 3.8
Classifier: Programming Language :: Python :: 3.9
Classifier: Programming Language :: Python :: 3.10
Classifier: Programming Language :: Python :: 3.11
Classifier: Programming Language :: Python :: 3.12
Requires-Python: >=3.8
